CHANGES.rst
LICENSE
MANIFEST.in
README
README.rst
requirements.txt
setup.py
trigrams/__init__.py
trigrams.egg-info/PKG-INFO
trigrams.egg-info/SOURCES.txt
trigrams.egg-info/dependency_links.txt
trigrams.egg-info/top_level.txt