Metadata-Version: 1.1
Name: trigrams
Version: 0.1.0
Summary: Simple trigrams-based text generation
Home-page: https://github.com/bfontaine/trigrams
Author: Baptiste Fontaine
Author-email: b@ptistefontaine.fr
License: Copyright © 2014 – Baptiste Fontaine
